{
  "version": "1",
  "target": "vsCode",
  "buildSystem": "makefile",
  "debugSupport": "none",
  "configurations": [
    {
      "name": "default",
      "guid": "cbbdf2d2-d86f-4cec-9837-f387f8933e79",
      "setupType": "expert",
      "coreBase": "C:\\Program Files (x86)\\Arduino\\hardware\\teensy\\avr",
      "compilerBase": "C:\\Program Files (x86)\\Arduino\\hardware\\tools\\arm",
      "makefileExtension": null,
      "copyCore": false,
      "sharedLibraries": [],
      "projectLibraries": [
        "Audio",
        "SD",
        "SerialFlash",
        "SPI",
        "Wire"
      ],
      "board": {
        "name": "Teensy 4.0",
        "options": {
          "USB Type": "Serial",
          "CPU Speed": "600 MHz",
          "Optimize": "Faster",
          "Keyboard Layout": "US English"
        }
      }
    }
  ]
}